dj_tailwind/__init__.py
dj_tailwind/apps.py
dj_tailwind/cookiecutter/cookiecutter.json
dj_tailwind/cookiecutter/{{cookiecutter.app_name}}/__init__.py
dj_tailwind/cookiecutter/{{cookiecutter.app_name}}/apps.py
dj_tailwind/cookiecutter/{{cookiecutter.app_name}}/package.json
dj_tailwind/cookiecutter/{{cookiecutter.app_name}}/postcss.config.js
dj_tailwind/cookiecutter/{{cookiecutter.app_name}}/tailwind.input.css
dj_tailwind/management/__init__.py
dj_tailwind/management/commands/__init__.py
dj_tailwind/management/commands/dj_tailwind.py
dj_tailwind/templatetags/__init__.py
dj_tailwind/templatetags/dj_tailwind_tags.py
dj_tailwind-0.1.1.dist-info/LICENSE
dj_tailwind-0.1.1.dist-info/METADATA
dj_tailwind-0.1.1.dist-info/WHEEL
dj_tailwind-0.1.1.dist-info/RECORD
