Metadata-Version: 2.3
Name: dj-tailwind
Version: 0.1.1
Summary: A Django project made to easier integrate Tailwind.
License: MIT
Keywords: Django,Tailwind
Author: Adin Hodovic
Author-email: hodovicadin@gmail.com
Requires-Python: >=3.10,<4.0
Classifier: Development Status :: 5 - Production/Stable
Classifier: Environment :: Web Environment
Classifier: Framework :: Django
Classifier: Framework :: Django :: 4.2
Classifier: Framework :: Django :: 5.0
Classifier: Intended Audience :: Developers
Classifier: License :: OSI Approved :: MIT License
Classifier: Operating System :: OS Independent
Classifier: Programming Language :: Python
Classifier: Programming Language :: Python :: 3
Classifier: Programming Language :: Python :: 3.10
Classifier: Programming Language :: Python :: 3.11
Classifier: Programming Language :: Python :: 3.12
Classifier: Programming Language :: Python :: 3.13
Requires-Dist: Django (>=5.1.7,<6.0.0)
Requires-Dist: django-click (>=2.4.1,<3.0.0)
Project-URL: Documentation, https://github.com/adinhodovic/dj-tailwind
Project-URL: Homepage, https://github.com/adinhodovic/dj-tailwind
Project-URL: Repository, https://github.com/adinhodovic/dj-tailwind
